skill_ip_address/LICENSE
skill_ip_address/LICENSE.md
skill_ip_address/README.md
skill_ip_address/__init__.py
skill_ip_address/skill.json
skill_ip_address/version.py
skill_ip_address/locale/ca-es/IP.voc
skill_ip_address/locale/ca-es/dot.dialog
skill_ip_address/locale/ca-es/my address is.dialog
skill_ip_address/locale/ca-es/my address on X is Y.dialog
skill_ip_address/locale/ca-es/no network connection.dialog
skill_ip_address/locale/ca-es/query.voc
skill_ip_address/locale/cs-cz/IP.voc
skill_ip_address/locale/cs-cz/dot.dialog
skill_ip_address/locale/cs-cz/my address is.dialog
skill_ip_address/locale/cs-cz/my address on X is Y.dialog
skill_ip_address/locale/cs-cz/no network connection.dialog
skill_ip_address/locale/cs-cz/query.voc
skill_ip_address/locale/de-de/IP.voc
skill_ip_address/locale/de-de/dot.dialog
skill_ip_address/locale/de-de/my address is.dialog
skill_ip_address/locale/de-de/my address on X is Y.dialog
skill_ip_address/locale/de-de/no network connection.dialog
skill_ip_address/locale/de-de/query.voc
skill_ip_address/locale/en-us/IP.voc
skill_ip_address/locale/en-us/dot.dialog
skill_ip_address/locale/en-us/my address is.dialog
skill_ip_address/locale/en-us/my address on X is Y.dialog
skill_ip_address/locale/en-us/no network connection.dialog
skill_ip_address/locale/en-us/public.voc
skill_ip_address/locale/en-us/query.voc
skill_ip_address/locale/en-us/word_local.dialog
skill_ip_address/locale/en-us/word_public.dialog
skill_ip_address/locale/es-es/IP.voc
skill_ip_address/locale/es-es/dot.dialog
skill_ip_address/locale/es-es/my address is.dialog
skill_ip_address/locale/es-es/my address on X is Y.dialog
skill_ip_address/locale/es-es/no network connection.dialog
skill_ip_address/locale/es-es/query.voc
skill_ip_address/locale/eu-eu/IP.voc
skill_ip_address/locale/eu-eu/dot.dialog
skill_ip_address/locale/eu-eu/my address is.dialog
skill_ip_address/locale/eu-eu/my address on X is Y.dialog
skill_ip_address/locale/eu-eu/no network connection.dialog
skill_ip_address/neon_skill_ip_address.egg-info/PKG-INFO
skill_ip_address/neon_skill_ip_address.egg-info/SOURCES.txt
skill_ip_address/neon_skill_ip_address.egg-info/dependency_links.txt
skill_ip_address/neon_skill_ip_address.egg-info/entry_points.txt
skill_ip_address/neon_skill_ip_address.egg-info/requires.txt
skill_ip_address/neon_skill_ip_address.egg-info/top_level.txt
neon_skill_ip_address-1.3.0.dist-info/LICENSE
neon_skill_ip_address-1.3.0.dist-info/LICENSE.md
neon_skill_ip_address-1.3.0.dist-info/METADATA
neon_skill_ip_address-1.3.0.dist-info/WHEEL
neon_skill_ip_address-1.3.0.dist-info/entry_points.txt
neon_skill_ip_address-1.3.0.dist-info/top_level.txt
neon_skill_ip_address-1.3.0.dist-info/RECORD
