Metadata-Version: 2.1
Name: neon-skill-ip-address
Version: 1.3.0
Summary: Neon IP Address Skill
Home-page: https://github.com/NeonGeckoCom/skill-ip_address
Author: Neongecko
Author-email: developers@neon.ai
License: BSD-3-Clause
License-File: LICENSE
License-File: LICENSE.md
Requires-Dist: requests~=2.20
Requires-Dist: ifaddr~=0.1
Requires-Dist: neon-utils~=1.12
Requires-Dist: ovos-utils>=0.0.28,~=0.0
Requires-Dist: ovos-bus-client>=0.0.5,~=0.0
Requires-Dist: ovos-workshop>=0.0.12,~=0.0
Provides-Extra: test
Requires-Dist: neon-minerva[padatious]~=0.3; extra == "test"
